garrett_status/__init__.py
garrett_status/__main__.py
garrett_status/app.py
garrett_status-0.1.1.dist-info/METADATA
garrett_status-0.1.1.dist-info/WHEEL
garrett_status-0.1.1.dist-info/entry_points.txt
garrett_status-0.1.1.dist-info/top_level.txt
garrett_status-0.1.1.dist-info/RECORD
