Metadata-Version: 2.4
Name: garrett-status
Version: 0.1.1
Summary: Check Garrett Remote Desktop user and system status
Author: Maroti Belge
Author-email: Your Name <your@email.com>
License: MIT
Requires-Python: >=3.6
Requires-Dist: flask
Dynamic: author
Dynamic: requires-python
